DerrickTools/__init__.py
DerrickTools/engine/__init__.py
DerrickTools/engine/datetime/__init__.py
DerrickTools/engine/datetime/main.py
DerrickTools/engine/secret/__init__.py
DerrickTools/engine/secret/main.py
derrick_tool-0.0.1.dist-info/LICENSE
derrick_tool-0.0.1.dist-info/METADATA
derrick_tool-0.0.1.dist-info/WHEEL
derrick_tool-0.0.1.dist-info/top_level.txt
derrick_tool-0.0.1.dist-info/RECORD
